dabih/__init__.py
dabih/__main__.py
dabih/config.py
dabih/logger.py
dabih/main.py
dabih/dabih_client/dabih_api_client/__init__.py
dabih/dabih_client/dabih_api_client/client.py
dabih/dabih_client/dabih_api_client/errors.py
dabih/dabih_client/dabih_api_client/py.typed
dabih/dabih_client/dabih_api_client/types.py
dabih/dabih_client/dabih_api_client/api/__init__.py
dabih/dabih_client/dabih_api_client/api/download/__init__.py
dabih/dabih_client/dabih_api_client/api/download/decrypt_dataset.py
dabih/dabih_client/dabih_api_client/api/download/download_chunk.py
dabih/dabih_client/dabih_api_client/api/download/download_dataset.py
dabih/dabih_client/dabih_api_client/api/filesystem/__init__.py
dabih/dabih_client/dabih_api_client/api/filesystem/add_directory.py
dabih/dabih_client/dabih_api_client/api/filesystem/add_members.py
dabih/dabih_client/dabih_api_client/api/filesystem/duplicate_inode.py
dabih/dabih_client/dabih_api_client/api/filesystem/file_info.py
dabih/dabih_client/dabih_api_client/api/filesystem/inode_tree.py
dabih/dabih_client/dabih_api_client/api/filesystem/list_files.py
dabih/dabih_client/dabih_api_client/api/filesystem/list_home.py
dabih/dabih_client/dabih_api_client/api/filesystem/list_inodes.py
dabih/dabih_client/dabih_api_client/api/filesystem/list_parents.py
dabih/dabih_client/dabih_api_client/api/filesystem/move_inode.py
dabih/dabih_client/dabih_api_client/api/filesystem/remove_inode.py
dabih/dabih_client/dabih_api_client/api/filesystem/search_cancel.py
dabih/dabih_client/dabih_api_client/api/filesystem/search_fs.py
dabih/dabih_client/dabih_api_client/api/filesystem/search_results.py
dabih/dabih_client/dabih_api_client/api/job/__init__.py
dabih/dabih_client/dabih_api_client/api/job/list_jobs.py
dabih/dabih_client/dabih_api_client/api/token/__init__.py
dabih/dabih_client/dabih_api_client/api/token/add_token.py
dabih/dabih_client/dabih_api_client/api/token/list_tokens.py
dabih/dabih_client/dabih_api_client/api/token/remove_token.py
dabih-1.0.2.dist-info/LICENSE
dabih-1.0.2.dist-info/METADATA
dabih-1.0.2.dist-info/WHEEL
dabih-1.0.2.dist-info/entry_points.txt
dabih-1.0.2.dist-info/top_level.txt
dabih-1.0.2.dist-info/RECORD
