Metadata-Version: 2.2
Name: dabih
Version: 1.0.2
Summary: A package to conveniently use the dabih API
Author-email: Charlotte Richter <hedwig-charlotte.richter@stud.uni-regensburg.de>
Project-URL: Homepage, https://github.com/charlotterchtr/dabih-python-package
Classifier: Programming Language :: Python :: 3
Classifier: License :: OSI Approved :: MIT License
Classifier: Operating System :: OS Independent
Requires-Python: >=3.7
License-File: LICENSE
Requires-Dist: click>=8.1.3
Requires-Dist: requests>=2.31.0
Requires-Dist: httpx<0.28.0,>=0.20.0
Requires-Dist: attrs>=21.3.0
Requires-Dist: python-dateutil>=2.8.0
Requires-Dist: pyyaml>=0.1.0
Requires-Dist: cryptography>=44.0.0
